langchain_rag/__init__.py
langchain_rag/document_transformers/__init__.py
langchain_rag/document_transformers/copy_transformer.py
langchain_rag/document_transformers/document_transform_pipeline.py
langchain_rag/document_transformers/document_transformers.py
langchain_rag/document_transformers/generate_questions.py
langchain_rag/document_transformers/lazy_document_transformer.py
langchain_rag/document_transformers/summarize_and_questions_transformer.py
langchain_rag/document_transformers/summarize_transformer.py
langchain_rag/vectorstores/__init__.py
langchain_rag/vectorstores/rag_vectorstore.py
langchain_rag/vectorstores/wrapper_vectorstore.py
langchain_rag-0.3.1.dist-info/LICENSE.txt
langchain_rag-0.3.1.dist-info/METADATA
langchain_rag-0.3.1.dist-info/WHEEL
langchain_rag-0.3.1.dist-info/RECORD
