Metadata-Version: 2.1
Name: langchain-rag
Version: 0.3.1
Summary: This is a temporary project while I wait for my langchain [pull-request](https://github.com/langchain-ai/langchain/pull/7278) to be validated.
Home-page: https://www.github.com/pprados/langchain-rag
License: Apache 2.0
Author: Philippe PRADOS
Requires-Python: >=3.9,<4.0
Classifier: License :: Other/Proprietary License
Classifier: Programming Language :: Python :: 3
Classifier: Programming Language :: Python :: 3.9
Classifier: Programming Language :: Python :: 3.10
Classifier: Programming Language :: Python :: 3.11
Classifier: Programming Language :: Python :: 3.12
Requires-Dist: jupyter (>=1.0.0,<2.0.0)
Requires-Dist: langchain (>=0.3.0)
Requires-Dist: langchain-community (>=0.3.0)
Requires-Dist: langchain-core (>=0.3.0)
Project-URL: Repository, https://www.github.com/pprados/langchain-rag
